bert_pytorch/__init__.py
bert_pytorch/__main__.py
bert_pytorch/dataset/__init__.py
bert_pytorch/dataset/dataset.py
bert_pytorch/dataset/vocab.py
bert_pytorch/model/__init__.py
bert_pytorch/model/bert.py
bert_pytorch/model/language_model.py
bert_pytorch/model/transformer.py
bert_pytorch/model/attention/__init__.py
bert_pytorch/model/attention/multi_head.py
bert_pytorch/model/attention/single.py
bert_pytorch/model/embedding/__init__.py
bert_pytorch/model/embedding/bert.py
bert_pytorch/model/embedding/position.py
bert_pytorch/model/embedding/segment.py
bert_pytorch/model/embedding/token.py
bert_pytorch/model/utils/__init__.py
bert_pytorch/model/utils/feed_forward.py
bert_pytorch/model/utils/gelu.py
bert_pytorch/model/utils/layer_norm.py
bert_pytorch/model/utils/sublayer.py
bert_pytorch/trainer/__init__.py
bert_pytorch/trainer/optim_schedule.py
bert_pytorch/trainer/pretrain.py
bert_pytorch-0.0.1a4.dist-info/DESCRIPTION.rst
bert_pytorch-0.0.1a4.dist-info/METADATA
bert_pytorch-0.0.1a4.dist-info/RECORD
bert_pytorch-0.0.1a4.dist-info/WHEEL
bert_pytorch-0.0.1a4.dist-info/entry_points.txt
bert_pytorch-0.0.1a4.dist-info/metadata.json
bert_pytorch-0.0.1a4.dist-info/top_level.txt
