Metadata-Version: 2.0
Name: bert-pytorch
Version: 0.0.1a4
Summary: Google AI 2018 BERT pytorch implementation
Home-page: https://github.com/codertimo/BERT-pytorch
Author: Junseong Kim
Author-email: codertimo@gmail.com
License: UNKNOWN
Platform: UNKNOWN
Classifier: Programming Language :: Python :: 3
Classifier: License :: OSI Approved :: Apache Software License
Classifier: Operating System :: OS Independent
Requires-Dist: numpy
Requires-Dist: torch (>=0.4.0)
Requires-Dist: tqdm
